ai_gateways-1.0.0.dist-info/licenses/LICENSE
gateways/__init__.py
gateways/gateway.py
ai_gateways-1.0.0.dist-info/METADATA
ai_gateways-1.0.0.dist-info/WHEEL
ai_gateways-1.0.0.dist-info/top_level.txt
ai_gateways-1.0.0.dist-info/RECORD
