Metadata-Version: 2.4
Name: ai-gateways
Version: 1.0.0
Summary: 统一的 AI Gateway 包，支持 Azure OpenAI、OpenRouter 和 Skywork 三种服务商
Home-page: https://github.com/yourusername/ai-gateways
Author: Your Name
Author-email: Your Name <your.email@example.com>
License: MIT
Project-URL: Homepage, https://github.com/yourusername/ai-gateways
Project-URL: Documentation, https://github.com/yourusername/ai-gateways#readme
Project-URL: Repository, https://github.com/yourusername/ai-gateways
Project-URL: Issues, https://github.com/yourusername/ai-gateways/issues
Keywords: ai,openai,azure,openrouter,skywork,llm,gpt,gemini
Classifier: Development Status :: 4 - Beta
Classifier: Intended Audience :: Developers
Classifier: License :: OSI Approved :: MIT License
Classifier: Programming Language :: Python :: 3
Classifier: Programming Language :: Python :: 3.8
Classifier: Programming Language :: Python :: 3.9
Classifier: Programming Language :: Python :: 3.10
Classifier: Programming Language :: Python :: 3.11
Classifier: Programming Language :: Python :: 3.12
Classifier: Programming Language :: Python :: 3.13
Classifier: Topic :: Software Development :: Libraries :: Python Modules
Classifier: Topic :: Scientific/Engineering :: Artificial Intelligence
Requires-Python: >=3.8
License-File: LICENSE
Requires-Dist: openai>=1.0.0
Requires-Dist: python-dotenv>=1.0.0
Requires-Dist: requests>=2.31.0
Requires-Dist: urllib3>=1.26.0
Provides-Extra: dev
Requires-Dist: pytest>=7.0.0; extra == "dev"
Requires-Dist: pytest-asyncio>=0.21.0; extra == "dev"
Dynamic: author
Dynamic: home-page
Dynamic: license-file
Dynamic: requires-python
